{"createdAt":"2024-07-23T20:43:40.715Z","updatedAt":"2024-07-25T16:30:33.000Z","id":"zNBNNPH87TgxjKHZ","name":"Chatwoot Pausa Despausa Chile","active":false,"nodes":[{"parameters":{"values":{"string":[{"name":"statustypebot","value":"={{ $('Webhook').item.json[\"body\"][\"custom_attributes\"][\"status_typebot\"] }}"},{"name":"numerowhats","value":"={{ $('Webhook').item.json[\"body\"][\"identifier\"] }}"},{"name":"urlapievolution","value":"https://api.witmovil.com"},{"name":"keyevolution","value":"evy6kxp7y5nmnwaa28lu"},{"name":"sessaoevolution","value":"NuntiusChile"}]},"options":{}},"id":"da0fae6f-7dad-43fb-8b31-bb2a3772d5ba","name":"Info","type":"n8n-nodes-base.set","typeVersion":2,"position":[20,600]},{"parameters":{"dataType":"string","value1":"={{ $('Webhook').item.json[\"body\"][\"custom_attributes\"][\"status_typebot\"] }}","rules":{"rules":[{"value2":"Desligado"},{"value2":"Ligado","output":1}]}},"id":"d7343ae3-c341-4fb0-a461-d42e0a7b08a9","name":"Switch","type":"n8n-nodes-base.switch","typeVersion":1,"position":[200,600]},{"parameters":{"method":"POST","url":"={{ $('Info').item.json[\"urlapievolution\"] }}/typebot/changeStatus/{{ $('Info').item.json[\"sessaoevolution\"] }}","sendHeaders":true,"headerParameters":{"parameters":[{"name":"apikey","value":"={{ $('Info').item.json[\"keyevolution\"] }}"}]},"sendBody":true,"specifyBody":"json","jsonBody":"={\n    \"remoteJid\": \"{{ $('Info').item.json[\"numerowhats\"] }}\",\n    \"status\": \"paused\"\n}","options":{}},"id":"d27a7f1d-dd92-413e-84a1-f513f059432e","name":"Pausa","type":"n8n-nodes-base.httpRequest","typeVersion":4.1,"position":[460,460]},{"parameters":{"method":"POST","url":"={{ $('Info').item.json[\"urlapievolution\"] }}/typebot/changeStatus/{{ $('Info').item.json[\"sessaoevolution\"] }}","sendHeaders":true,"headerParameters":{"parameters":[{"name":"apikey","value":"={{ $('Info').item.json[\"keyevolution\"] }}"}]},"sendBody":true,"specifyBody":"json","jsonBody":"={\n    \"remoteJid\": \"{{ $('Info').item.json[\"numerowhats\"] }}\",\n    \"status\": \"closed\"\n}","options":{}},"id":"1cd7cf7a-2b1e-43c1-b8e7-757916a25636","name":"Inicia","type":"n8n-nodes-base.httpRequest","typeVersion":4.1,"position":[460,680]},{"parameters":{"conditions":{"string":[{"value1":"={{ $json.body.changed_attributes[1].custom_attributes }}","operation":"isNotEmpty"}]}},"id":"0cf44be2-c863-45ee-b0e6-cee65219433d","name":"IF","type":"n8n-nodes-base.if","typeVersion":1,"position":[-200,620]},{"parameters":{"httpMethod":"POST","path":"fbe45400-3165-4b6c-8476-900cf2063c35","options":{}},"id":"503ec3fa-7a65-48b9-a3df-42a455700743","name":"Webhook","type":"n8n-nodes-base.webhook","typeVersion":1,"position":[-420,620],"webhookId":"fbe45400-3165-4b6c-8476-900cf2063c35"}],"connections":{"Info":{"main":[[{"node":"Switch","type":"main","index":0}]]},"Switch":{"main":[[{"node":"Pausa","type":"main","index":0}],[{"node":"Inicia","type":"main","index":0}]]},"IF":{"main":[[{"node":"Info","type":"main","index":0}]]},"Webhook":{"main":[[{"node":"IF","type":"main","index":0}]]}},"settings":{"executionOrder":"v1"},"staticData":null,"meta":{"templateCredsSetupCompleted":true},"pinData":{},"versionId":"6330eb5a-3c42-4e79-8600-cc8bffa9f2b7","triggerCount":1,"tags":[]}